{"errors":[],"warnings":[],"namedChunkGroups":{"app":{"chunks":[6,0,2],"assets":["webpack-runtime-69c492a63743d63d8bc4.js","webpack-runtime-69c492a63743d63d8bc4.js.map","commons-36fa055b4e54fde13fc5.js","commons-36fa055b4e54fde13fc5.js.map","app-de8b9992be488eab7543.js","app-de8b9992be488eab7543.js.map"],"children":{},"childAssets":{}},"component---src-templates-portfolio-tsx":{"chunks":[1,0,5],"assets":["styles.b76e6118434ce301e804.css","styles-2062fa5e3a11f3742554.js","styles-2062fa5e3a11f3742554.js.map","commons-36fa055b4e54fde13fc5.js","commons-36fa055b4e54fde13fc5.js.map","component---src-templates-portfolio-tsx-1eef65e13fb7fc920998.js","component---src-templates-portfolio-tsx-1eef65e13fb7fc920998.js.map"],"children":{},"childAssets":{}},"component---src-pages-404-tsx":{"chunks":[1,0,3],"assets":["styles.b76e6118434ce301e804.css","styles-2062fa5e3a11f3742554.js","styles-2062fa5e3a11f3742554.js.map","commons-36fa055b4e54fde13fc5.js","commons-36fa055b4e54fde13fc5.js.map","component---src-pages-404-tsx-836d3c1d6d60589806ad.js","component---src-pages-404-tsx-836d3c1d6d60589806ad.js.map"],"children":{},"childAssets":{}},"component---src-pages-index-tsx":{"chunks":[1,0,4],"assets":["styles.b76e6118434ce301e804.css","styles-2062fa5e3a11f3742554.js","styles-2062fa5e3a11f3742554.js.map","commons-36fa055b4e54fde13fc5.js","commons-36fa055b4e54fde13fc5.js.map","component---src-pages-index-tsx-43cc7382412519ef74cd.js","component---src-pages-index-tsx-43cc7382412519ef74cd.js.map"],"children":{},"childAssets":{}}},"assetsByChunkName":{"app":["webpack-runtime-69c492a63743d63d8bc4.js","commons-36fa055b4e54fde13fc5.js","app-de8b9992be488eab7543.js"],"component---src-templates-portfolio-tsx":["styles.b76e6118434ce301e804.css","styles-2062fa5e3a11f3742554.js","commons-36fa055b4e54fde13fc5.js","component---src-templates-portfolio-tsx-1eef65e13fb7fc920998.js"],"component---src-pages-404-tsx":["styles.b76e6118434ce301e804.css","styles-2062fa5e3a11f3742554.js","commons-36fa055b4e54fde13fc5.js","component---src-pages-404-tsx-836d3c1d6d60589806ad.js"],"component---src-pages-index-tsx":["styles.b76e6118434ce301e804.css","styles-2062fa5e3a11f3742554.js","commons-36fa055b4e54fde13fc5.js","component---src-pages-index-tsx-43cc7382412519ef74cd.js"]}}